Workbook

Sheet Start Here
B1: Start | D1: Dashboard | F1: Pipeline | H1: Jobs | J1: Invoices | L1: Settings
B2: RELIABLE SOURCES — COMMAND CENTER
B3: Who to chase today, what work is live, who owes you money — in under a minute.
B5: The 5-Minute Morning Routine
B7: 1. Open the Dashboard tab and read the tiles — they update themselves.
B8: 2. Check 'Follow-ups due' — call or WhatsApp each CALL TODAY lead in the Pipeline tab, update its stage, and set the next follow-up date.
B9: 3. Glance at overdue invoices on the Dashboard — chase the oldest one first.
B10: 4. New enquiry since yesterday? Log it in the Pipeline tab — one row, 30 seconds.
B12: What each tab does
B13: Dashboard — your morning read. All formulas, nothing to type.
B14: Pipeline — every enquiry and quote. Blue cells are yours to type; grey ones fill themselves.
B15: Jobs — won work only, with margin worked out for you.
B16: Invoices — what you've billed, what's been paid, what's overdue.
... B21: Blue writing on cream = type here. Everything else is locked so it can't break. Dummy data is loaded — replace it with your real pipeline.

Sheet Dashboard
B1: Start | D1: Dashboard | F1: Pipeline | H1: Jobs | J1: Invoices | L1: Settings
B2: DASHBOARD — read it, don't type in it
B3: Updates itself from Pipeline, Jobs and Invoices. Amounts in AED.
B5: Follow-ups due today / overdue | C5: =COUNTIF(Pipeline!$M$5:$M$304,"CALL TODAY")
B7: Open pipeline (count) | C7: =COUNTIFS(Pipeline!$I$5:$I$304,"<>",Pipeline!$I$5:$I$304,"<>"&Settings!$G$14,Pipeline!$I$5:$I$304,"<>"&Settings!$G$15) | E7: Open pipeline AED | F7: =SUMIFS(Pipeline!$H$5:$H$304,Pipeline!$I$5:$I$304,"<>",Pipeline!$I$5:$I$304,"<>"&Settings!$G$14,Pipeline!$I$5:$I$304,"<>"&Settings!$G$15) | H7: Weighted pipeline AED | I7: =SUMIFS(Pipeline!$K$5:$K$304,Pipeline!$I$5:$I$304,"<>",Pipeline!$I$5:$I$304,"<>"&Settings!$G$14,Pipeline!$I$5:$I$304,"<>"&Settings!$G$15)
B9: New leads this month | C9: =COUNTIFS(Pipeline!$B$5:$B$304,">="&DATE(YEAR(TODAY()),MONTH(TODAY()),1),Pipeline!$B$5:$B$304,"<"&EDATE(DATE(YEAR(TODAY()),MONTH(TODAY()),1),1)) | E9: Jobs won this month (count) | F9: =COUNTIFS(Jobs!$J$5:$J$204,">="&DATE(YEAR(TODAY()),MONTH(TODAY()),1),Jobs!$J$5:$J$204,"<"&EDATE(DATE(YEAR(TODAY()),MONTH(TODAY()),1),1)) | H9: Jobs won this month AED | I9: =SUMIFS(Jobs!$E$5:$E$204,Jobs!$J$5:$J$204,">="&DATE(YEAR(TODAY()),MONTH(TODAY()),1),Jobs!$J$5:$J$204,"<"&EDATE(DATE(YEAR(TODAY()),MONTH(TODAY()),1),1))
B11: Win rate (won ÷ closed) | C11: =IF(COUNTIF(Pipeline!$I$5:$I$304,Settings!$G$14)+COUNTIF(Pipeline!$I$5:$I$304,Settings!$G$15)=0,0,COUNTIF(Pipeline!$I$5:$I$304,Settings!$G$14)/(COUNTIF(Pipeline!$I$5:$I$304,Settings!$G$14)+COUNTIF(Pipeline!$I$5:$I$304,Settings!$G$15))) | E11: Invoiced this month AED | F11: =SUMIFS(Invoices!$F$5:$F$204,Invoices!$E$5:$E$204,">="&DATE(YEAR(TODAY()),MONTH(TODAY()),1),Invoices!$E$5:$E$204,"<"&EDATE(DATE(YEAR(TODAY()),MONTH(TODAY()),1),1)) | H11: Collected this month AED | I11: =SUMIFS(Invoices!$G$5:$G$204,Invoices!$H$5:$H$204,">="&DATE(YEAR(TODAY()),MONTH(TODAY()),1),Invoices!$H$5:$H$204,"<"&EDATE(DATE(YEAR(TODAY()),MONTH(TODAY()),1),1))
B13: Total outstanding AED | C13: =SUM(Invoices!$I$5:$I$204) | E13: Overdue AED | F13: =SUMIFS(Invoices!$I$5:$I$204,Invoices!$K$5:$K$204,"Overdue")
B15: PIPELINE BY BUSINESS LINE
B16: Business line | C16: Open pipeline AED | D16: Won this year AED | E16: Open pipeline
B17: =IF(Settings!$C$10="","",Settings!$C$10) | C17: =IF($B17="","",SUMIFS(Pipeline!$H$5:$H$304,Pipeline!$E$5:$E$304,$B17,Pipeline!$I$5:$I$304,"<>",Pipeline!$I$5:$I$304,"<>"&Settings!$G$14,Pipeline!$I$5:$I$304,"<>"&Settings!$G$15)) | D17: =IF($B17="","",SUMIFS(Jobs!$E$5:$E$204,Jobs!$D$5:$D$204,$B17,Jobs!$J$5:$J$204,">="&DATE(YEAR(TODAY()),1,1),Jobs!$J$5:$J$204,"<"&DATE(YEAR(TODAY())+1,1,1))) | E17: =IF(OR($B17="",MAX($C$17:$C$20)=0),"",REPT("█",ROUND($C17/MAX($C$17:$C$20)*20,0)))
B18: =IF(Settings!$C$11="","",Settings!$C$11) | C18: =IF($B18="","",SUMIFS(Pipeline!$H$5:$H$304,Pipeline!$E$5:$E$304,$B18,Pipeline!$I$5:$I$304,"<>",Pipeline!$I$5:$I$304,"<>"&Settings!$G$14,Pipeline!$I$5:$I$304,"<>"&Settings!$G$15)) | D18: =IF($B18="","",SUMIFS(Jobs!$E$5:$E$204,Jobs!$D$5:$D$204,$B18,Jobs!$J$5:$J$204,">="&DATE(YEAR(TODAY()),1,1),Jobs!$J$5:$J$204,"<"&DATE(YEAR(TODAY())+1,1,1))) | E18: =IF(OR($B18="",MAX($C$17:$C$20)=0),"",REPT("█",ROUND($C18/MAX($C$17:$C$20)*20,0)))
B19: =IF(Settings!$C$12="","",Settings!$C$12) | C19: =IF($B19="","",SUMIFS(Pipeline!$H$5:$H$304,Pipeline!$E$5:$E$304,$B19,Pipeline!$I$5:$I$304,"<>",Pipeline!$I$5:$I$304,"<>"&Settings!$G$14,Pipeline!$I$5:$I$304,"<>"&Settings!$G$15)) | D19: =IF($B19="","",SUMIFS(Jobs!$E$5:$E$204,Jobs!$D$5:$D$204,$B19,Jobs!$J$5:$J$204,">="&DATE(YEAR(TODAY()),1,1),Jobs!$J$5:$J$204,"<"&DATE(YEAR(TODAY())+1,1,1))) | E19: =IF(OR($B19="",MAX($C$17:$C$20)=0),"",REPT("█",ROUND($C19/MAX($C$17:$C$20)*20,0)))
B20: =IF(Settings!$C$13="","",Settings!$C$13) | C20: =IF($B20="","",SUMIFS(Pipeline!$H$5:$H$304,Pipeline!$E$5:$E$304,$B20,Pipeline!$I$5:$I$304,"<>",Pipeline!$I$5:$I$304,"<>"&Settings!$G$14,Pipeline!$I$5:$I$304,"<>"&Settings!$G$15)) | D20: =IF($B20="","",SUMIFS(Jobs!$E$5:$E$204,Jobs!$D$5:$D$204,$B20,Jobs!$J$5:$J$204,">="&DATE(YEAR(TODAY()),1,1),Jobs!$J$5:$J$204,"<"&DATE(YEAR(TODAY())+1,1,1))) | E20: =IF(OR($B20="",MAX($C$17:$C$20)=0),"",REPT("█",ROUND($C20/MAX($C$17:$C$20)*20,0)))
B22: Red tile means pick up the phone. The chart and this table follow whatever names you give your business lines in Settings.

Sheet Pipeline
B1: Start | D1: Dashboard | F1: Pipeline | H1: Jobs | J1: Invoices | L1: Settings
B2: PIPELINE — every enquiry lives here
B3: Blue cells are yours. Probability, weighted value and the CALL TODAY flag fill themselves.
B4: Date in | C4: Client | D4: Contact | E4: Business line | F4: Source | G4: What they want | H4: Est. value AED | I4: Stage | J4: Probability % | K4: Weighted AED | L4: Next follow-up | M4: Status flag | N4: Notes
B5: 46188 | C5: Al Noor Cafe - Marina | D5: Fatima R. | E5: Signage | F5: Google Ads | G5: Shopfront sign + menu boards | H5: 18500 | I5: Quote sent | J5: =IF($I5="","",IFERROR(VLOOKUP($I5,Settings!$G$10:$H$15,2,FALSE),"")) | K5: =IF(OR($H5="",$J5=""),"",$H5*$J5) | L5: 46205 | M5: =IF(OR($I5="",$L5=""),"",IF(AND($L5<=TODAY(),$I5<>Settings!$G$14,$I5<>Settings!$G$15),"CALL TODAY","")) | N5: Wants LED letters, budget conscious
B6: 46193 | C6: Dr. Salem Dental Clinic | D6: Dr. Salem | E6: Fitout | F6: Referral | G6: Reception + waiting area fitout | H6: 95000 | I6: Negotiating | J6: =IF($I6="","",IFERROR(VLOOKUP($I6,Settings!$G$10:$H$15,2,FALSE),"")) | K6: =IF(OR($H6="",$J6=""),"",$H6*$J6) | L6: 46209 | M6: =IF(OR($I6="",$L6=""),"",IF(AND($L6<=TODAY(),$I6<>Settings!$G$14,$I6<>Settings!$G$15),"CALL TODAY","")) | N6: Comparing two quotes
B7: 46204 | C7: Marina Gym Co. | D7: Omar K. | E7: Neon | F7: Instagram | G7: Neon logo wall for reception | H7: 7800 | I7: New | J7: =IF($I7="","",IFERROR(VLOOKUP($I7,Settings!$G$10:$H$15,2,FALSE),"")) | K7: =IF(OR($H7="",$J7=""),"",$H7*$J7) | L7: 46208 | M7: =IF(OR($I7="",$L7=""),"",IF(AND($L7<=TODAY(),$I7<>Settings!$G$14,$I7<>Settings!$G$15),"CALL TODAY","")) | N7: DM enquiry, send portfolio
B8: 46201 | C8: Lulu Mini Mart | D8: Anil P. | E8: Signage | F8: Walk-in | G8: Pylon sign refresh | H8: 24000 | I8: Contacted | J8: =IF($I8="","",IFERROR(VLOOKUP($I8,Settings!$G$10:$H$15,2,FALSE),"")) | K8: =IF(OR($H8="",$J8=""),"",$H8*$J8) | L8: 46210 | M8: =IF(OR($I8="",$L8=""),"",IF(AND($L8<=TODAY(),$I8<>Settings!$G$14,$I8<>Settings!$G$15),"CALL TODAY","")) | N8: Site visit done, measuring next
B9: 46205 | C9: Bloom Flower Boutique | D9: Sara M. | E9: Website | F9: Designer partner | G9: 5-page brochure site | H9: 6500 | I9: New | J9: =IF($I9="","",IFERROR(VLOOKUP($I9,Settings!$G$10:$H$15,2,FALSE),"")) | K9: =IF(OR($H9="",$J9=""),"",$H9*$J9) | L9: 46207 | M9: =IF(OR($I9="",$L9=""),"",IF(AND($L9<=TODAY(),$I9<>Settings!$G$14,$I9<>Settings!$G$15),"CALL TODAY","")) | N9: Referred by Layla (designer)
B10: 46183 | C10: Desert Rose Salon | D10: Mariam A. | E10: Neon | F10: Instagram | G10: Custom neon sign for wall | H10: 5200 | I10: Quote sent | J10: =IF($I10="","",IFERROR(VLOOKUP($I10,Settings!$G$10:$H$15,2,FALSE),"")) | K10: =IF(OR($H10="",$J10=""),"",$H10*$J10) | L10: 46211 | M10: =IF(OR($I10="",$L10=""),"",IF(AND($L10<=TODAY(),$I10<>Settings!$G$14,$I10<>Settings!$G$15),"CALL TODAY","")) | N10: Quote sent 25/06
B11: 46191 | C11: Gulf Auto Detailing | D11: Khalid S. | E11: Signage | F11: Google Ads | G11: Full branding + workshop signage | H11: 32000 | I11: Negotiating | J11: =IF($I11="","",IFERROR(VLOOKUP($I11,Settings!$G$10:$H$15,2,FALSE),"")) | K11: =IF(OR($H11="",$J11=""),"",$H11*$J11) | L11: 46212 | M11: =IF(OR($I11="",$L11=""),"",IF(AND($L11<=TODAY(),$I11<>Settings!$G$14,$I11<>Settings!$G$15),"CALL TODAY","")) | N11: Wants phased delivery
B12: 46198 | C12: Sunrise Nursery | D12: Huda N. | E12: Fitout | F12: Existing client | G12: Two-classroom fitout | H12: 68000 | I12: Contacted | J12: =IF($I12="","",IFERROR(VLOOKUP($I12,Settings!$G$10:$H$15,2,FALSE),"")) | K12: =IF(OR($H12="",$J12=""),"",$H12*$J12) | L12: 46213 | M12: =IF(OR($I12="",$L12=""),"",IF(AND($L12<=TODAY(),$I12<>Settings!$G$14,$I12<>Settings!$G$15),"CALL TODAY","")) | N12: Repeat client, summer window
B13: 46185 | C13: Kaya Beach Restaurant | D13: Joseph T. | E13: Signage | F13: Referral | G13: Illuminated fascia sign | H13: 21000 | I13: Won | J13: =IF($I13="","",IFERROR(VLOOKUP($I13,Settings!$G$10:$H$15,2,FALSE),"")) | K13: =IF(OR($H13="",$J13=""),"",$H13*$J13) | M13: =IF(OR($I13="",$L13=""),"",IF(AND($L13<=TODAY(),$I13<>Settings!$G$14,$I13<>Settings!$G$15),"CALL TODAY","")) | N13: Now job RS-001
B14: 46178 | C14: Falcon Real Estate | D14: Ahmed B. | E14: Website | F14: Google Ads | G14: Landing page for tower launch | H14: 4000 | I14: Lost | J14: =IF($I14="","",IFERROR(VLOOKUP($I14,Settings!$G$10:$H$15,2,FALSE),"")) | K14: =IF(OR($H14="",$J14=""),"",$H14*$J14) | M14: =IF(OR($I14="",$L14=""),"",IF(AND($L14<=TODAY(),$I14<>Settings!$G$14,$I14<>Settings!$G$15),"CALL TODAY","")) | N14: Went with agency
J15: =IF($I15="","",IFERROR(VLOOKUP($I15,Settings!$G$10:$H$15,2,FALSE),"")) | K15: =IF(OR($H15="",$J15=""),"",$H15*$J15) | M15: =IF(OR($I15="",$L15=""),"",IF(AND($L15<=TODAY(),$I15<>Settings!$G$14,$I15<>Settings!$G$15),"CALL TODAY",""))
J16: =IF($I16="","",IFERROR(VLOOKUP($I16,Settings!$G$10:$H$15,2,FALSE),"")) | K16: =IF(OR($H16="",$J16=""),"",$H16*$J16) | M16: =IF(OR($I16="",$L16=""),"",IF(AND($L16<=TODAY(),$I16<>Settings!$G$14,$I16<>Settings!$G$15),"CALL TODAY",""))
J17: =IF($I17="","",IFERROR(VLOOKUP($I17,Settings!$G$10:$H$15,2,FALSE),"")) | K17: =IF(OR($H17="",$J17=""),"",$H17*$J17) | M17: =IF(OR($I17="",$L17=""),"",IF(AND($L17<=TODAY(),$I17<>Settings!$G$14,$I17<>Settings!$G$15),"CALL TODAY",""))
J18: =IF($I18="","",IFERROR(VLOOKUP($I18,Settings!$G$10:$H$15,2,FALSE),"")) | K18: =IF(OR($H18="",$J18=""),"",$H18*$J18) | M18: =IF(OR($I18="",$L18=""),"",IF(AND($L18<=TODAY(),$I18<>Settings!$G$14,$I18<>Settings!$G$15),"CALL TODAY",""))
J19: =IF($I19="","",IFERROR(VLOOKUP($I19,Settings!$G$10:$H$15,2,FALSE),"")) | K19: =IF(OR($H19="",$J19=""),"",$H19*$J19) | M19: =IF(OR($I19="",$L19=""),"",IF(AND($L19<=TODAY(),$I19<>Settings!$G$14,$I19<>Settings!$G$15),"CALL TODAY",""))
J20: =IF($I20="","",IFERROR(VLOOKUP($I20,Settings!$G$10:$H$15,2,FALSE),"")) | K20: =IF(OR($H20="",$J20=""),"",$H20*$J20) | M20: =IF(OR($I20="",$L20=""),"",IF(AND($L20<=TODAY(),$I20<>Settings!$G$14,$I20<>Settings!$G$15),"CALL TODAY",""))
J21: =IF($I21="","",IFERROR(VLOOKUP($I21,Settings!$G$10:$H$15,2,FALSE),"")) | K21: =IF(OR($H21="",$J21=""),"",$H21*$J21) | M21: =IF(OR($I21="",$L21=""),"",IF(AND($L21<=TODAY(),$I21<>Settings!$G$14,$I21<>Settings!$G$15),"CALL TODAY",""))
J22: =IF($I22="","",IFERROR(VLOOKUP($I22,Settings!$G$10:$H$15,2,FALSE),"")) | K22: =IF(OR($H22="",$J22=""),"",$H22*$J22) | M22: =IF(OR($I22="",$L22=""),"",IF(AND($L22<=TODAY(),$I22<>Settings!$G$14,$I22<>Settings!$G$15),"CALL TODAY",""))
J23: =IF($I23="","",IFERROR(VLOOKUP($I23,Settings!$G$10:$H$15,2,FALSE),"")) | K23: =IF(OR($H23="",$J23=""),"",$H23*$J23) | M23: =IF(OR($I23="",$L23=""),"",IF(AND($L23<=TODAY(),$I23<>Settings!$G$14,$I23<>Settings!$G$15),"CALL TODAY",""))
J24: =IF($I24="","",IFERROR(VLOOKUP($I24,Settings!$G$10:$H$15,2,FALSE),"")) | K24: =IF(OR($H24="",$J24=""),"",$H24*$J24) | M24: =IF(OR($I24="",$L24=""),"",IF(AND($L24<=TODAY(),$I24<>Settings!$G$14,$I24<>Settings!$G$15),"CALL TODAY",""))
J25: =IF($I25="","",IFERROR(VLOOKUP($I25,Settings!$G$10:$H$15,2,FALSE),"")) | K25: =IF(OR($H25="",$J25=""),"",$H25*$J25) | M25: =IF(OR($I25="",$L25=""),"",IF(AND($L25<=TODAY(),$I25<>Settings!$G$14,$I25<>Settings!$G$15),"CALL TODAY",""))
J26: =IF($I26="","",IFERROR(VLOOKUP($I26,Settings!$G$10:$H$15,2,FALSE),"")) | K26: =IF(OR($H26="",$J26=""),"",$H26*$J26) | M26: =IF(OR($I26="",$L26=""),"",IF(AND($L26<=TODAY(),$I26<>Settings!$G$14,$I26<>Settings!$G$15),"CALL TODAY",""))
... J304: =IF($I304="","",IFERROR(VLOOKUP($I304,Settings!$G$10:$H$15,2,FALSE),"")) | K304: =IF(OR($H304="",$J304=""),"",$H304*$J304) | M304: =IF(OR($I304="",$L304=""),"",IF(AND($L304<=TODAY(),$I304<>Settings!$G$14,$I304<>Settings!$G$15),"CALL TODAY",""))

Sheet Jobs
B1: Start | D1: Dashboard | F1: Pipeline | H1: Jobs | J1: Invoices | L1: Settings
B2: JOBS — won work only
B3: Job ref and margin fill themselves. Type the rest.
B4: Job ref | C4: Client | D4: Business line | E4: Value AED | F4: Est. cost AED | G4: Margin AED | H4: Margin % | I4: Status | J4: Start date | K4: Handover date | L4: Notes
B5: =IF($C5="","","RS-"&TEXT(ROW()-4,"000")) | C5: Kaya Beach Restaurant | D5: Signage | E5: 21000 | F5: 12600 | G5: =IF(OR($E5="",$F5=""),"",$E5-$F5) | H5: =IF(OR($E5="",$E5=0,$G5=""),"",$G5/$E5) | I5: In progress | J5: 46195 | K5: 46218 | L5: Fascia fabrication underway
B6: =IF($C6="","","RS-"&TEXT(ROW()-4,"000")) | C6: Emirates Hills Villa 27 | D6: Fitout | E6: 140000 | F6: 98000 | G6: =IF(OR($E6="",$F6=""),"",$E6-$F6) | H6: =IF(OR($E6="",$E6=0,$G6=""),"",$G6/$E6) | I6: In progress | J6: 46174 | K6: 46254 | L6: Majlis + garden room
B7: =IF($C7="","","RS-"&TEXT(ROW()-4,"000")) | C7: Blue Pearl Spa | D7: Neon | E7: 9500 | F7: 4700 | G7: =IF(OR($E7="",$F7=""),"",$E7-$F7) | H7: =IF(OR($E7="",$E7=0,$G7=""),"",$G7/$E7) | I7: Done | J7: 46147 | K7: 46162 | L7: Handed over, client happy
B8: =IF($C8="","","RS-"&TEXT(ROW()-4,"000")) | C8: Zaitoon Grill House | D8: Signage | E8: 27500 | F8: 16200 | G8: =IF(OR($E8="",$F8=""),"",$E8-$F8) | H8: =IF(OR($E8="",$E8=0,$G8=""),"",$G8/$E8) | I8: Done | J8: 46122 | K8: 46147 | L8: Fascia + interior menu boards
B9: =IF($C9="","","RS-"&TEXT(ROW()-4,"000")) | C9: Coral Bay Dental | D9: Website | E9: 5800 | F9: 1200 | G9: =IF(OR($E9="",$F9=""),"",$E9-$F9) | H9: =IF(OR($E9="",$E9=0,$G9=""),"",$G9/$E9) | I9: In progress | J9: 46205 | K9: 46219 | L9: Content received
B10: =IF($C10="","","RS-"&TEXT(ROW()-4,"000")) | G10: =IF(OR($E10="",$F10=""),"",$E10-$F10) | H10: =IF(OR($E10="",$E10=0,$G10=""),"",$G10/$E10)
B11: =IF($C11="","","RS-"&TEXT(ROW()-4,"000")) | G11: =IF(OR($E11="",$F11=""),"",$E11-$F11) | H11: =IF(OR($E11="",$E11=0,$G11=""),"",$G11/$E11)
B12: =IF($C12="","","RS-"&TEXT(ROW()-4,"000")) | G12: =IF(OR($E12="",$F12=""),"",$E12-$F12) | H12: =IF(OR($E12="",$E12=0,$G12=""),"",$G12/$E12)
B13: =IF($C13="","","RS-"&TEXT(ROW()-4,"000")) | G13: =IF(OR($E13="",$F13=""),"",$E13-$F13) | H13: =IF(OR($E13="",$E13=0,$G13=""),"",$G13/$E13)
B14: =IF($C14="","","RS-"&TEXT(ROW()-4,"000")) | G14: =IF(OR($E14="",$F14=""),"",$E14-$F14) | H14: =IF(OR($E14="",$E14=0,$G14=""),"",$G14/$E14)
B15: =IF($C15="","","RS-"&TEXT(ROW()-4,"000")) | G15: =IF(OR($E15="",$F15=""),"",$E15-$F15) | H15: =IF(OR($E15="",$E15=0,$G15=""),"",$G15/$E15)
B16: =IF($C16="","","RS-"&TEXT(ROW()-4,"000")) | G16: =IF(OR($E16="",$F16=""),"",$E16-$F16) | H16: =IF(OR($E16="",$E16=0,$G16=""),"",$G16/$E16)
B17: =IF($C17="","","RS-"&TEXT(ROW()-4,"000")) | G17: =IF(OR($E17="",$F17=""),"",$E17-$F17) | H17: =IF(OR($E17="",$E17=0,$G17=""),"",$G17/$E17)
B18: =IF($C18="","","RS-"&TEXT(ROW()-4,"000")) | G18: =IF(OR($E18="",$F18=""),"",$E18-$F18) | H18: =IF(OR($E18="",$E18=0,$G18=""),"",$G18/$E18)
B19: =IF($C19="","","RS-"&TEXT(ROW()-4,"000")) | G19: =IF(OR($E19="",$F19=""),"",$E19-$F19) | H19: =IF(OR($E19="",$E19=0,$G19=""),"",$G19/$E19)
B20: =IF($C20="","","RS-"&TEXT(ROW()-4,"000")) | G20: =IF(OR($E20="",$F20=""),"",$E20-$F20) | H20: =IF(OR($E20="",$E20=0,$G20=""),"",$G20/$E20)
B21: =IF($C21="","","RS-"&TEXT(ROW()-4,"000")) | G21: =IF(OR($E21="",$F21=""),"",$E21-$F21) | H21: =IF(OR($E21="",$E21=0,$G21=""),"",$G21/$E21)
... B204: =IF($C204="","","RS-"&TEXT(ROW()-4,"000")) | G204: =IF(OR($E204="",$F204=""),"",$E204-$F204) | H204: =IF(OR($E204="",$E204=0,$G204=""),"",$G204/$E204)

Sheet Invoices
B1: Start | D1: Dashboard | F1: Pipeline | H1: Jobs | J1: Invoices | L1: Settings
B2: INVOICES — who owes you money
B3: Balance, status and days overdue fill themselves. Overdue rows turn red, paid rows green.
B4: Invoice # | C4: Client | D4: Job ref | E4: Invoice date | F4: Amount AED | G4: Paid AED | H4: Paid date | I4: Balance AED | J4: Due date | K4: Status | L4: Days overdue | M4: Notes
B5: INV-2026-041 | C5: Zaitoon Grill House | D5: RS-004 | E5: 46124 | F5: 27500 | G5: 27500 | H5: 46147 | I5: =IF($F5="","",$F5-N($G5)) | J5: 46152 | K5: =IF($F5="","",IF($I5<=0,"Paid",IF(AND($J5<>"",TODAY()>$J5),"Overdue",IF(N($G5)>0,"Partial","Upcoming")))) | L5: =IF(OR($F5="",$I5<=0,$J5=""),"",IF(TODAY()>$J5,TODAY()-$J5,"")) | M5: Closed
B6: INV-2026-042 | C6: Blue Pearl Spa | D6: RS-003 | E6: 46148 | F6: 9500 | G6: 9500 | H6: 46170 | I6: =IF($F6="","",$F6-N($G6)) | J6: 46174 | K6: =IF($F6="","",IF($I6<=0,"Paid",IF(AND($J6<>"",TODAY()>$J6),"Overdue",IF(N($G6)>0,"Partial","Upcoming")))) | L6: =IF(OR($F6="",$I6<=0,$J6=""),"",IF(TODAY()>$J6,TODAY()-$J6,"")) | M6: Closed
B7: INV-2026-043 | C7: Emirates Hills Villa 27 | D7: RS-002 | E7: 46174 | F7: 70000 | G7: 35000 | H7: 46193 | I7: =IF($F7="","",$F7-N($G7)) | J7: 46188 | K7: =IF($F7="","",IF($I7<=0,"Paid",IF(AND($J7<>"",TODAY()>$J7),"Overdue",IF(N($G7)>0,"Partial","Upcoming")))) | L7: =IF(OR($F7="",$I7<=0,$J7=""),"",IF(TODAY()>$J7,TODAY()-$J7,"")) | M7: Progress payment 1 of 2
B8: INV-2026-044 | C8: Kaya Beach Restaurant | D8: RS-001 | E8: 46195 | F8: 10500 | G8: 0 | I8: =IF($F8="","",$F8-N($G8)) | J8: 46201 | K8: =IF($F8="","",IF($I8<=0,"Paid",IF(AND($J8<>"",TODAY()>$J8),"Overdue",IF(N($G8)>0,"Partial","Upcoming")))) | L8: =IF(OR($F8="",$I8<=0,$J8=""),"",IF(TODAY()>$J8,TODAY()-$J8,"")) | M8: 50% advance - chase
B9: INV-2026-045 | C9: Coral Bay Dental | D9: RS-005 | E9: 46206 | F9: 2900 | G9: 1500 | H9: 46207 | I9: =IF($F9="","",$F9-N($G9)) | J9: 46223 | K9: =IF($F9="","",IF($I9<=0,"Paid",IF(AND($J9<>"",TODAY()>$J9),"Overdue",IF(N($G9)>0,"Partial","Upcoming")))) | L9: =IF(OR($F9="",$I9<=0,$J9=""),"",IF(TODAY()>$J9,TODAY()-$J9,"")) | M9: Deposit received
B10: INV-2026-046 | C10: Emirates Hills Villa 27 | D10: RS-002 | E10: 46204 | F10: 35000 | G10: 0 | I10: =IF($F10="","",$F10-N($G10)) | J10: 46228 | K10: =IF($F10="","",IF($I10<=0,"Paid",IF(AND($J10<>"",TODAY()>$J10),"Overdue",IF(N($G10)>0,"Partial","Upcoming")))) | L10: =IF(OR($F10="",$I10<=0,$J10=""),"",IF(TODAY()>$J10,TODAY()-$J10,"")) | M10: Progress payment 2 of 2
I11: =IF($F11="","",$F11-N($G11)) | K11: =IF($F11="","",IF($I11<=0,"Paid",IF(AND($J11<>"",TODAY()>$J11),"Overdue",IF(N($G11)>0,"Partial","Upcoming")))) | L11: =IF(OR($F11="",$I11<=0,$J11=""),"",IF(TODAY()>$J11,TODAY()-$J11,""))
I12: =IF($F12="","",$F12-N($G12)) | K12: =IF($F12="","",IF($I12<=0,"Paid",IF(AND($J12<>"",TODAY()>$J12),"Overdue",IF(N($G12)>0,"Partial","Upcoming")))) | L12: =IF(OR($F12="",$I12<=0,$J12=""),"",IF(TODAY()>$J12,TODAY()-$J12,""))
I13: =IF($F13="","",$F13-N($G13)) | K13: =IF($F13="","",IF($I13<=0,"Paid",IF(AND($J13<>"",TODAY()>$J13),"Overdue",IF(N($G13)>0,"Partial","Upcoming")))) | L13: =IF(OR($F13="",$I13<=0,$J13=""),"",IF(TODAY()>$J13,TODAY()-$J13,""))
I14: =IF($F14="","",$F14-N($G14)) | K14: =IF($F14="","",IF($I14<=0,"Paid",IF(AND($J14<>"",TODAY()>$J14),"Overdue",IF(N($G14)>0,"Partial","Upcoming")))) | L14: =IF(OR($F14="",$I14<=0,$J14=""),"",IF(TODAY()>$J14,TODAY()-$J14,""))
I15: =IF($F15="","",$F15-N($G15)) | K15: =IF($F15="","",IF($I15<=0,"Paid",IF(AND($J15<>"",TODAY()>$J15),"Overdue",IF(N($G15)>0,"Partial","Upcoming")))) | L15: =IF(OR($F15="",$I15<=0,$J15=""),"",IF(TODAY()>$J15,TODAY()-$J15,""))
I16: =IF($F16="","",$F16-N($G16)) | K16: =IF($F16="","",IF($I16<=0,"Paid",IF(AND($J16<>"",TODAY()>$J16),"Overdue",IF(N($G16)>0,"Partial","Upcoming")))) | L16: =IF(OR($F16="",$I16<=0,$J16=""),"",IF(TODAY()>$J16,TODAY()-$J16,""))
I17: =IF($F17="","",$F17-N($G17)) | K17: =IF($F17="","",IF($I17<=0,"Paid",IF(AND($J17<>"",TODAY()>$J17),"Overdue",IF(N($G17)>0,"Partial","Upcoming")))) | L17: =IF(OR($F17="",$I17<=0,$J17=""),"",IF(TODAY()>$J17,TODAY()-$J17,""))
I18: =IF($F18="","",$F18-N($G18)) | K18: =IF($F18="","",IF($I18<=0,"Paid",IF(AND($J18<>"",TODAY()>$J18),"Overdue",IF(N($G18)>0,"Partial","Upcoming")))) | L18: =IF(OR($F18="",$I18<=0,$J18=""),"",IF(TODAY()>$J18,TODAY()-$J18,""))
I19: =IF($F19="","",$F19-N($G19)) | K19: =IF($F19="","",IF($I19<=0,"Paid",IF(AND($J19<>"",TODAY()>$J19),"Overdue",IF(N($G19)>0,"Partial","Upcoming")))) | L19: =IF(OR($F19="",$I19<=0,$J19=""),"",IF(TODAY()>$J19,TODAY()-$J19,""))
I20: =IF($F20="","",$F20-N($G20)) | K20: =IF($F20="","",IF($I20<=0,"Paid",IF(AND($J20<>"",TODAY()>$J20),"Overdue",IF(N($G20)>0,"Partial","Upcoming")))) | L20: =IF(OR($F20="",$I20<=0,$J20=""),"",IF(TODAY()>$J20,TODAY()-$J20,""))
I21: =IF($F21="","",$F21-N($G21)) | K21: =IF($F21="","",IF($I21<=0,"Paid",IF(AND($J21<>"",TODAY()>$J21),"Overdue",IF(N($G21)>0,"Partial","Upcoming")))) | L21: =IF(OR($F21="",$I21<=0,$J21=""),"",IF(TODAY()>$J21,TODAY()-$J21,""))
I22: =IF($F22="","",$F22-N($G22)) | K22: =IF($F22="","",IF($I22<=0,"Paid",IF(AND($J22<>"",TODAY()>$J22),"Overdue",IF(N($G22)>0,"Partial","Upcoming")))) | L22: =IF(OR($F22="",$I22<=0,$J22=""),"",IF(TODAY()>$J22,TODAY()-$J22,""))
... I204: =IF($F204="","",$F204-N($G204)) | K204: =IF($F204="","",IF($I204<=0,"Paid",IF(AND($J204<>"",TODAY()>$J204),"Overdue",IF(N($G204)>0,"Partial","Upcoming")))) | L204: =IF(OR($F204="",$I204<=0,$J204=""),"",IF(TODAY()>$J204,TODAY()-$J204,""))

Sheet Settings
B1: Start | D1: Dashboard | F1: Pipeline | H1: Jobs | J1: Invoices | L1: Settings
B2: SETTINGS
B3: Rename lists here — dropdowns and formulas follow automatically.
B5: Currency label | C5: AED
B6: VAT note | C6: VAT 5% — prices exclude VAT unless stated
C9: Business lines | E9: Lead sources | G9: Stage | H9: Probability | J9: Job status
C10: Signage | E10: Google Ads | G10: New | H10: 0.1 | J10: In progress
C11: Neon | E11: Instagram | G11: Contacted | H11: 0.25 | J11: Done
C12: Fitout | E12: Referral | G12: Quote sent | H12: 0.4
C13: Website | E13: Walk-in | G13: Negotiating | H13: 0.6
E14: Existing client | G14: Won | H14: 1
E15: Designer partner | G15: Lost | H15: 0
B17: Stages Won and Lost count as closed. A lead in any other stage is open pipeline.
